kamal_in_states/__init__.py
kamal_in_states/asgi.py
kamal_in_states/settings.py
kamal_in_states/urls.py
kamal_in_states/wsgi.py
states/__init__.py
states/admin.py
states/apps.py
states/models.py
states/tests.py
states/views.py
states/migrations/__init__.py
kamal_in_states-0.1.dist-info/METADATA
kamal_in_states-0.1.dist-info/WHEEL
kamal_in_states-0.1.dist-info/top_level.txt
kamal_in_states-0.1.dist-info/RECORD
